metachat/__init__.py
metachat/_optimal_transport/__init__.py
metachat/_optimal_transport/_cot.py
metachat/_optimal_transport/_fot.py
metachat/_optimal_transport/_unot.py
metachat/_optimal_transport/_usot.py
metachat/_utils/__init__.py
metachat/_utils/_clustering.py
metachat/_utils/_plotting.py
metachat/plotting/__init__.py
metachat/plotting/_plotting.py
metachat/preprocessing/_MetaChatDB.py
metachat/preprocessing/__init__.py
metachat/preprocessing/_computeCost.py
metachat/preprocessing/_computeLR.py
metachat/preprocessing/_identifyLRC.py
metachat/preprocessing/_importData.py
metachat/preprocessing/_preprocess.py
metachat/preprocessing/_data/MetaChatDB/MetaChatDB_human.csv
metachat/preprocessing/_data/MetaChatDB/MetaChatDB_mouse.csv
metachat/tools/__init__.py
metachat/tools/_downstream_analysis.py
metachat/tools/_spatial_communication.py
metachat-0.0.6.dist-info/LICENSE.md
metachat-0.0.6.dist-info/METADATA
metachat-0.0.6.dist-info/WHEEL
metachat-0.0.6.dist-info/top_level.txt
metachat-0.0.6.dist-info/RECORD
