Metadata-Version: 2.1
Name: metachat
Version: 0.0.6
Summary: Spatial metabolic communication flow of cells.
Home-page: https://https://github.com/SonghaoLuo/metachat
Author: Songhao Luo
Author-email: songhal2@@uci.edu
License: MIT License
Keywords: metabolic cell communicaiton,spatial transcriptomics,spatial metabolomics,optimal transport
Classifier: Programming Language :: Python :: 3.9
Classifier: License :: OSI Approved :: MIT License
Classifier: Operating System :: POSIX :: Linux
Classifier: Operating System :: MacOS
Classifier: Topic :: Scientific/Engineering
Classifier: Topic :: Scientific/Engineering :: Bio-Informatics
Requires-Python: >=3.9
License-File: LICENSE.md
Requires-Dist: adjustText==1.3.0
Requires-Dist: anndata==0.10.8
Requires-Dist: anndata2ri==1.3.1
Requires-Dist: gseapy==1.1.2
Requires-Dist: leidenalg==0.10.2
Requires-Dist: matplotlib==3.8.4
Requires-Dist: networkx==3.2.1
Requires-Dist: numpy==1.23.1
Requires-Dist: pandas==2.3.1
Requires-Dist: plotly==5.21.0
Requires-Dist: POT==0.9.3
Requires-Dist: pycirclize==1.6.0
Requires-Dist: pydpc==0.1.3
Requires-Dist: python-igraph==0.11.4
Requires-Dist: rpy2==3.5.15
Requires-Dist: scanpy==1.10.1
Requires-Dist: scikit-learn==1.4.2
Requires-Dist: scipy==1.13.1
Requires-Dist: seaborn==0.13.2
Requires-Dist: squidpy==1.2.2
Requires-Dist: tqdm==4.66.2
Provides-Extra: docs
Requires-Dist: sphinx==5.3.0; extra == "docs"
Requires-Dist: sphinx-autodoc-typehints==1.18.1; extra == "docs"
Requires-Dist: sphinx-rtd-theme==1.0.0; extra == "docs"
Requires-Dist: sphinx-rtd-size==0.2.0; extra == "docs"
Requires-Dist: sphinxcontrib-applehelp==1.0.2; extra == "docs"
Requires-Dist: sphinxcontrib-devhelp==1.0.2; extra == "docs"
Requires-Dist: sphinxcontrib-htmlhelp==2.0.0; extra == "docs"
Requires-Dist: sphinxcontrib-jsmath==1.0.1; extra == "docs"
Requires-Dist: sphinxcontrib-qthelp==1.0.3; extra == "docs"
Requires-Dist: sphinxcontrib-serializinghtml==1.1.5; extra == "docs"
Requires-Dist: sphinx-mdinclude==0.5.3; extra == "docs"
Requires-Dist: nbsphinx==0.8.9; extra == "docs"
Requires-Dist: ipykernel==6.16.0; extra == "docs"
Requires-Dist: sphinx-gallery==0.11.1; extra == "docs"
